indentpy/__init__.py
indentpy/indent.py
indentpy-1.0.0.dist-info/METADATA
indentpy-1.0.0.dist-info/RECORD
indentpy-1.0.0.dist-info/WHEEL
indentpy-1.0.0.dist-info/top_level.txt
