Metadata-Version: 2.1
Name: indentpy
Version: 1.0.0
Summary: Python utility to change indentations of files.
Home-page: https://github.com/Thijsvanede/indentpy
Author: Thijs van Ede
Author-email: t.s.vanede@utwente.nl
License: UNKNOWN
Platform: UNKNOWN
Classifier: Programming Language :: Python :: 3
Classifier: License :: OSI Approved :: MIT License
Classifier: Operating System :: OS Independent
